fellow_py/__init__.py
fellow_py/discover.py
fellow_py/exceptions.py
fellow_py/kettle.py
fellow_py-0.2.3.dist-info/LICENSE
fellow_py-0.2.3.dist-info/METADATA
fellow_py-0.2.3.dist-info/WHEEL
fellow_py-0.2.3.dist-info/top_level.txt
fellow_py-0.2.3.dist-info/RECORD
