Metadata-Version: 2.1
Name: fellow-py
Version: 0.2.3
Summary: Library to control Fellow Stagg Kettle EKG+
Home-page: https://github.com/justin-richert/fellow-py
Author: Justin Richert
Author-email: justinrichert@icloud.com
License: MIT License
Keywords: fellow
Platform: UNKNOWN
Classifier: Development Status :: 4 - Beta
Classifier: Intended Audience :: Developers
Classifier: License :: OSI Approved :: MIT License
Classifier: Natural Language :: English
Classifier: Programming Language :: Python :: 3
Classifier: Programming Language :: Python :: 3.6
Classifier: Programming Language :: Python :: 3.7
Classifier: Programming Language :: Python :: 3.8
Requires-Python: >=3.6
Requires-Dist: bleak (>=0.10.0)
